stacrs-0.5.9.dist-info/METADATA
stacrs-0.5.9.dist-info/WHEEL
stacrs-0.5.9.dist-info/entry_points.txt
stacrs-0.5.9.dist-info/licenses/LICENSE-APACHE
stacrs-0.5.9.dist-info/licenses/LICENSE-MIT
stacrs/__init__.py
stacrs/__init__.pyi
stacrs/py.typed
stacrs/stacrs.cpython-310-darwin.so
stacrs-0.5.9.dist-info/RECORD
